datalaunch/__init__.py
datalaunch/_version.py
datalaunch-0.0.1.dist-info/LICENSE
datalaunch-0.0.1.dist-info/METADATA
datalaunch-0.0.1.dist-info/WHEEL
datalaunch-0.0.1.dist-info/top_level.txt
datalaunch-0.0.1.dist-info/RECORD
